aiofasttelethonhelper/__init__.py
aiofasttelethonhelper/utils.py
aiofasttelethonhelper/core/__init__.py
aiofasttelethonhelper/core/methods.py
aiofasttelethonhelper/core/senders.py
aiofasttelethonhelper/core/transfer.py
aiofasttelethonhelper/core/types.py
aiofasttelethonhelper/core/util.py
aiofasttelethonhelper-0.1.3.dist-info/licenses/LICENSE
aiofasttelethonhelper-0.1.3.dist-info/METADATA
aiofasttelethonhelper-0.1.3.dist-info/WHEEL
aiofasttelethonhelper-0.1.3.dist-info/top_level.txt
aiofasttelethonhelper-0.1.3.dist-info/RECORD
