Metadata-Version: 2.4
Name: aiofasttelethonhelper
Version: 0.1.3
Summary: Fully async and parallel file upload/download in Telethon, without blocking the event loop.
Author-email: Aron1cX <aron1cx.dev@gmail.com>
License-Expression: MIT
Project-URL: Homepage, https://github.com/aron1cx/AIOFastTelethonHelper
Project-URL: Issues, https://github.com/aron1cx/AIOFastTelethonHelper/issues
Project-URL: Source, https://github.com/aron1cx/AIOFastTelethonHelper
Keywords: telethon,fasttelethonhelper,aio,async,telegram,selfbot,userbot
Classifier: Programming Language :: Python :: 3
Classifier: Operating System :: OS Independent
Requires-Python: >=3.9
License-File: LICENSE
Requires-Dist: aiofiles==24.1.0
Requires-Dist: setuptools>=80.9.0
Requires-Dist: telethon>=1.41.2
Dynamic: license-file
